putupy/__init__.py
putupy/base.py
putupy/firstmodule/__init__.py
putupy/firstmodule/fmodule.py
putupy-0.0.2.dist-info/LICENSE
putupy-0.0.2.dist-info/METADATA
putupy-0.0.2.dist-info/WHEEL
putupy-0.0.2.dist-info/top_level.txt
putupy-0.0.2.dist-info/RECORD
