Metadata-Version: 2.1
Name: putupy
Version: 0.0.2
Summary: A small example package
Author-email: Putu Widyantara <putuwaw973@gmail.com>
Project-URL: Homepage, https://github.com/putuwaw/putupy
Project-URL: Bug Tracker, https://github.com/putuwaw/putupy
Classifier: Programming Language :: Python :: 3
Classifier: License :: OSI Approved :: MIT License
Classifier: Operating System :: OS Independent
Requires-Python: >=3.7
License-File: LICENSE
